Metadata-Version: 2.1
Name: oneNeuron-pypi-dipdregan
Version: 0.0.3
Summary: It's implementation of perceptron
Home-page: https://github.com/dipdregan/oneNeuron_pypi
Author: Dipendra Pratap
License: UNKNOWN
Project-URL: Bug Tracker, https://github.com/dipdregan/oneNeuron_pypit/issues
Platform: UNKNOWN
Classifier: Programming Language :: Python :: 3
Classifier: License :: OSI Approved :: MIT License
Classifier: Operating System :: OS Independent
Requires-Python: >=3.6
License-File: LICENSE
Requires-Dist: numpy
Requires-Dist: tqdm
Requires-Dist: logging
